Metadata-Version: 1.1
Name: napa
Version: 1.3
Summary: Network Analysis of Protein Adaptation (intra-protein residue coevolution network construction and analysis)
Home-page: http://karchinlab.org/apps/appNapa.html
Author: Violeta Beleva Guthrie
Author-email: vbeleva@gmail.com
License: UNKNOWN
Platform: UNKNOWN
Classifier: Development Status :: 5 - Production/Stable
Classifier: Intended Audience :: Developers
Classifier: Topic :: Scientific/Engineering :: Bio-Informatics
